tabsdata_agent-1.5.0.data/purelib/tabsdata_agent/__init__.py
tabsdata_agent-1.5.0.data/purelib/tabsdata_agent/__spec.py
tabsdata_agent-1.5.0.data/purelib/tabsdata_agent/_core/__init__.py
tabsdata_agent-1.5.0.data/purelib/tabsdata_agent/_core/agent.py
tabsdata_agent-1.5.0.data/purelib/tabsdata_agent/_core/client.py
tabsdata_agent-1.5.0.data/purelib/tabsdata_agent/_core/constants.py
tabsdata_agent-1.5.0.data/purelib/tabsdata_agent/_core/server.py
tabsdata_agent-1.5.0.data/purelib/tabsdata_agent/_core/utils.py
tabsdata_agent-1.5.0.data/purelib/tabsdata_agent/_core/faiss/__init__.py
tabsdata_agent-1.5.0.data/purelib/tabsdata_agent/_core/faiss/embed_faiss.py
tabsdata_agent-1.5.0.data/purelib/tabsdata_agent/_core/tools/__init__.py
tabsdata_agent-1.5.0.data/purelib/tabsdata_agent/_core/tools/rag.py
tabsdata_agent-1.5.0.data/purelib/tabsdata_agent/_core/tools/tabsdata.py
tabsdata_agent-1.5.0.data/purelib/tabsdata_agent/api/__init__.py
tabsdata_agent-1.5.0.data/purelib/tabsdata_agent/assets/manifest/BANNER
tabsdata_agent-1.5.0.data/purelib/tabsdata_agent/assets/manifest/LICENSE
tabsdata_agent-1.5.0.data/purelib/tabsdata_agent/assets/manifest/LICENSE.setup
tabsdata_agent-1.5.0.data/purelib/tabsdata_agent/assets/manifest/PYDOC.csv
tabsdata_agent-1.5.0.data/purelib/tabsdata_agent/assets/manifest/README-PyPi.md
tabsdata_agent-1.5.0.data/purelib/tabsdata_agent/assets/manifest/RELEASE-NOTES
tabsdata_agent-1.5.0.data/purelib/tabsdata_agent/assets/manifest/THIRD-PARTY
tabsdata_agent-1.5.0.data/purelib/tabsdata_agent/resources/faiss/index.faiss
tabsdata_agent-1.5.0.data/purelib/tabsdata_agent/resources/faiss/index.pkl
tabsdata_agent-1.5.0.data/purelib/tabsdata_agent/resources/registry/prompts/rag_prompt.txt
tabsdata_agent-1.5.0.data/purelib/tabsdata_agent/resources/registry/prompts/system_prompt.txt
tabsdata_agent-1.5.0.data/purelib/tabsdata_agent/resources/registry/status/execution_plan.yaml
tabsdata_agent-1.5.0.data/purelib/tabsdata_agent/resources/registry/status/function.yaml
tabsdata_agent-1.5.0.dist-info/licenses/variant/assets/manifest/LICENSE
tabsdata_agent-1.5.0.dist-info/METADATA
tabsdata_agent-1.5.0.dist-info/WHEEL
tabsdata_agent-1.5.0.dist-info/entry_points.txt
tabsdata_agent-1.5.0.dist-info/top_level.txt
tabsdata_agent-1.5.0.dist-info/RECORD
